hyutil_hoyun_lab/__init__.py
hyutil_hoyun_lab/analysis.py
hyutil_hoyun_lab/appcontrol.py
hyutil_hoyun_lab/augmentjob.py
hyutil_hoyun_lab/date_time.py
hyutil_hoyun_lab/dirjob.py
hyutil_hoyun_lab/filejob.py
hyutil_hoyun_lab/hashing.py
hyutil_hoyun_lab/tfrecrod_utils.py
hyutil_hoyun_lab/xml_util.py
hyutils_hyutil_hoyun_lab-0.1.0.3.dist-info/LICENSE.txt
hyutils_hyutil_hoyun_lab-0.1.0.3.dist-info/METADATA
hyutils_hyutil_hoyun_lab-0.1.0.3.dist-info/WHEEL
hyutils_hyutil_hoyun_lab-0.1.0.3.dist-info/top_level.txt
hyutils_hyutil_hoyun_lab-0.1.0.3.dist-info/RECORD
