Metadata-Version: 2.1
Name: hyutils-hyutil-hoyun-lab
Version: 0.1.0.3
Summary: Hoyun Lab Python Utils
Home-page: https://www.hoyun.co.kr
Author: nohgan im
Author-email: fory2k@hoyun.co.kr
License: MIT
Project-URL: Bug Tracker, https://github.com/schooldevops/python-tutorials/issues
Classifier: Programming Language :: Python :: 3
Classifier: License :: OSI Approved :: MIT License
Classifier: Operating System :: OS Independent
Requires-Python: >=3.6
License-File: LICENSE.txt
